src/__init__.py
src/vkLibrary.py
vkLibrary-0.0.2.dist-info/METADATA
vkLibrary-0.0.2.dist-info/RECORD
vkLibrary-0.0.2.dist-info/WHEEL
vkLibrary-0.0.2.dist-info/top_level.txt
