Metadata-Version: 2.1
Name: vkLibrary
Version: 0.0.2
Summary: vk library package
Home-page: https://github.com/petukhovlive/vkLibrary
Author: Dmitry Petukhov
Author-email: petumit@yandex.ru
License: UNKNOWN
Platform: UNKNOWN
Classifier: Programming Language :: Python :: 3
Classifier: License :: OSI Approved :: MIT License
Classifier: Operating System :: OS Independent
